{
    "timesteps_": 1300,
    "stepsize_": 0.001,
    "substeps_": 1,
    "processesX_": 3,
    "processesY_": 3,
    "processesZ_": 3,
    "seed_": 12345,
    "verbose_": false,
    "vtk_": true,
    "visspacing_": 50,
    "pointerspacing_": 100,
    "useCheckpointer_": false,
    "resume_": false,
    "checkpoint_path_": "checkpoints/",
    "volumeFraction_": 0.3,
    "benchRadius_": 0.0075,
    "benchStartPosition_": [1.0, 0.01, 0.1275],
    "packingMethod_": "grid",
    "xyzFilePath_": "",
    "particleDensity_": 1120.0,
    "fluidViscosity_": 0.058,
    "fluidDensity_": 960.0,
    "gravity_": [0.0, 0.0, -9.81],
    "lubricationHysteresisDelta_": 1e-3,
    "contactHysteresisDelta_": 1e-9,
    "alphaImpulseCap_": 1.0,
    "minEpsLub_": 1e-8
}
